pystf/__init__.py
pystf/base.py
pystf/exceptions.py
pystf/renderers.py
pystf/transformers.py
pystf/types.py
pystf/utils.py
pystf-0.0.1.dist-info/LICENSE
pystf-0.0.1.dist-info/METADATA
pystf-0.0.1.dist-info/WHEEL
pystf-0.0.1.dist-info/RECORD
